iscc_service/__init__.py
iscc_service/config.py
iscc_service/conn.py
iscc_service/main.py
iscc_service/models.py
iscc_service/tools.py
iscc_service-0.2.3.dist-info/entry_points.txt
iscc_service-0.2.3.dist-info/LICENSE
iscc_service-0.2.3.dist-info/WHEEL
iscc_service-0.2.3.dist-info/METADATA
iscc_service-0.2.3.dist-info/RECORD
