Metadata-Version: 2.1
Name: iscc-service
Version: 0.2.3
Summary: ISCC Web Service API
Home-page: https://iscc.codes/
License: MIT
Keywords: iscc,media,identifier,blockchain,cli,generator,webservice,api
Author: Titusz Pan
Author-email: tp@py7.de
Requires-Python: >=3.6,<4.0
Classifier: Development Status :: 4 - Beta
Classifier: Intended Audience :: Developers
Classifier: License :: OSI Approved :: MIT License
Classifier: Programming Language :: Python :: 3
Classifier: Programming Language :: Python :: 3 :: Only
Classifier: Programming Language :: Python :: 3.6
Classifier: Programming Language :: Python :: 3.7
Classifier: Programming Language :: Python :: 3.8
Classifier: Topic :: Adaptive Technologies
Classifier: Topic :: Internet
Classifier: Topic :: Internet :: WWW/HTTP :: Indexing/Search
Classifier: Topic :: Internet :: WWW/HTTP :: WSGI :: Application
Classifier: Topic :: Multimedia
Classifier: Topic :: Multimedia :: Sound/Audio :: Analysis
Classifier: Topic :: Scientific/Engineering :: Information Analysis
Classifier: Topic :: System :: Distributed Computing
Classifier: Topic :: Text Processing :: Indexing
Requires-Dist: bitstring (>=3.1,<4.0)
Requires-Dist: fastapi (>=0.54,<0.55)
Requires-Dist: iscc-cli (>=0.9,<0.10)
Requires-Dist: jmespath (>=0.9,<0.10)
Requires-Dist: loguru (>=0.4,<0.5)
Requires-Dist: mcrpc (>=2.0,<3.0)
Requires-Dist: python-multipart (>=0.0.5,<0.0.6)
Requires-Dist: uvicorn (>=0.11,<0.12)
Project-URL: Documentation, https://github.com/iscc/iscc-service
Project-URL: Repository, https://github.com/iscc/iscc-service
